pythermal/__init__.py
pythermal/commands.py
pythermal/live_view.py
pythermal/record.py
pythermal/_native/armLinux/enumerate_devices
pythermal/_native/armLinux/libHCUSBSDK.so
pythermal/_native/armLinux/libhpr.so
pythermal/_native/armLinux/libusb-1.0.so
pythermal/_native/armLinux/libusb-1.0.so.0
pythermal/_native/armLinux/libusb-1.0.so.0.2.0
pythermal/_native/armLinux/libuvc.so
pythermal/_native/armLinux/pythermal-recorder
pythermal/_native/linux64/enumerate_devices
pythermal/_native/linux64/libHCUSBSDK.so
pythermal/_native/linux64/libHCUSBSDK.sym
pythermal/_native/linux64/libhpr.so
pythermal/_native/linux64/libusb-1.0.so
pythermal/_native/linux64/libusb-1.0.so.0
pythermal/_native/linux64/libusb-1.0.so.0.2.0
pythermal/_native/linux64/libuvc.so
pythermal/_native/linux64/log4cxx.properties
pythermal/_native/linux64/pythermal-recorder
pythermal/core/__init__.py
pythermal/core/capture.py
pythermal/core/device.py
pythermal/core/device_enumerator.py
pythermal/core/device_manager.py
pythermal/core/enumerate_devices.py
pythermal/core/frame_processor.py
pythermal/core/sequence_reader.py
pythermal/core/thermal_shared_memory.py
pythermal/detections/__init__.py
pythermal/detections/motion_detection.py
pythermal/detections/roi.py
pythermal/detections/temperature_detection.py
pythermal/detections/utils.py
pythermal/detections/yolo/__init__.py
pythermal/detections/yolo/object_detection.py
pythermal/detections/yolo/pose_detection.py
pythermal/detections/yolo/segmentation.py
pythermal/synthesis/__init__.py
pythermal/synthesis/frame_generator.py
pythermal/synthesis/human_segmentation.py
pythermal/synthesis/image_processor.py
pythermal/synthesis/synthetic_generator.py
pythermal/synthesis/temperature_mapper.py
pythermal/usb_setup/99-thermal-camera.rules
pythermal/usb_setup/setup-thermal-permissions.sh
pythermal/usb_setup/setup.sh
pythermal/utils/__init__.py
pythermal/utils/environment.py
pythermal-0.2.11.dist-info/licenses/LICENSE
pythermal-0.2.11.dist-info/METADATA
pythermal-0.2.11.dist-info/WHEEL
pythermal-0.2.11.dist-info/entry_points.txt
pythermal-0.2.11.dist-info/top_level.txt
pythermal-0.2.11.dist-info/RECORD
