Metadata-Version: 2.4
Name: pythermal
Version: 0.2.11
Summary: A lightweight Python library for thermal sensing and analytics on Linux platforms
Home-page: https://github.com/AIoT-Infrastructure/pythermal
Author: ThermalCare Team
Author-email: yunqiguo@cuhk.edu.hk
Project-URL: Documentation, https://aiot-infrastructure.github.io/pythermal/
Project-URL: Source, https://github.com/AIoT-Infrastructure/pythermal
Project-URL: Bug Tracker, https://github.com/AIoT-Infrastructure/pythermal/issues
Classifier: Development Status :: 3 - Alpha
Classifier: Intended Audience :: Developers
Classifier: Intended Audience :: Science/Research
Classifier: License :: OSI Approved :: Apache Software License
Classifier: Operating System :: POSIX :: Linux
Classifier: Programming Language :: Python :: 3
Classifier: Programming Language :: Python :: 3.9
Classifier: Programming Language :: Python :: 3.10
Classifier: Programming Language :: Python :: 3.11
Classifier: Topic :: Scientific/Engineering :: Image Processing
Classifier: Topic :: Multimedia :: Video :: Capture
Requires-Python: >=3.9
License-File: LICENSE
Requires-Dist: numpy>=1.20.0
Requires-Dist: opencv-python>=4.5.0
Provides-Extra: dev
Requires-Dist: pytest>=7.0.0; extra == "dev"
Requires-Dist: pytest-cov>=4.0.0; extra == "dev"
Requires-Dist: black>=22.0.0; extra == "dev"
Requires-Dist: flake8>=5.0.0; extra == "dev"
Provides-Extra: yolo
Requires-Dist: ultralytics>=8.0.0; extra == "yolo"
Dynamic: author
Dynamic: author-email
Dynamic: classifier
Dynamic: description
Dynamic: description-content-type
Dynamic: home-page
Dynamic: license-file
Dynamic: project-url
Dynamic: provides-extra
Dynamic: requires-dist
Dynamic: requires-python
Dynamic: summary
